certReportCentral/__init__.py
certReportCentral/main.py
certreportcentral-0.1.1.dist-info/METADATA
certreportcentral-0.1.1.dist-info/WHEEL
certreportcentral-0.1.1.dist-info/entry_points.txt
certreportcentral-0.1.1.dist-info/top_level.txt
certreportcentral-0.1.1.dist-info/RECORD
