Metadata-Version: 2.4
Name: certReportCentral
Version: 0.1.1
Summary: DEPRECIATED: This tool is fully superceeded by certReport.
Author-email: Squiblydoo <Squiblydoo@pm.me>
Project-URL: Homepage, https://github.com/Squiblydoo/certReportCentral
Project-URL: Bug Tracker, https://github.com/Squiblydoo/certReportCentral/issues
Classifier: Programming Language :: Python :: 3
Classifier: License :: OSI Approved :: BSD License
Classifier: Operating System :: OS Independent
Requires-Python: >=3.8
Requires-Dist: requests>=2.32.1
